[
    {
      "dir": "disk0\/00\/00\/63\/74",
      "publication": "JOD Fisip Unbara",
      "divisions": [
        "FISIP3"
      ],
      "status_changed": "2018-01-29 04:11:24",
      "full_text_status": "public",
      "issn": "1979–0899X",
      "ispublished": "pub",
      "rev_number": 7,
      "subjects": [
        "JC"
      ],
      "date_type": "published",
      "volume": 4,
      "abstract": "The emergence of global governance as the needs of \"legitimacy\" of the norms in force in the world at\r\nthat time. Term of the legitimacy is the product of the politics that provide justification. Global\r\ngovernance is seen more as a political product rather than as a concept is useful as a source of\r\nlegitimacy. Governance issues reduced a political as a concept, mechanism and process of\r\nreorganizing the world to be more open to the market.\r\nKeywords: Global governance, legitimacy, a product of politics, liberalism",
      "uri": "http:\/\/repository.lppm.unila.ac.id\/id\/eprint\/6374",
      "date": "2011-12-30",
      "creators": [
        {
          "name": {
            "given": "Robi",
            "honourific": null,
            "lineage": null,
            "family": "Cahyadi"
          },
          "id": "robi_ck@yahoo.com"
        }
      ],
      "type": "article",
      "refereed": "TRUE",
      "title": "Global Governance: Perspektif Liberalisme",
      "eprint_status": "archive",
      "eprintid": 6374,
      "datestamp": "2018-01-29 04:11:24",
      "pagerange": "1-7",
      "metadata_visibility": "show",
      "number": 8,
      "userid": 680,
      "documents": [
          {
            "uri": "http:\/\/repository.lppm.unila.ac.id\/id\/document\/19298",
            "pos": 1,
            "security": "public",
            "placement": 1,
            "eprintid": 6374,
            "mime_type": "application\/pdf",
            "language": "en",
            "rev_number": 1,
            "docid": 19298,
            "main": "Global Governance (unbara).pdf",
            "files": [
                {
                  "objectid": 19298,
                  "filesize": 317166,
                  "uri": "http:\/\/repository.lppm.unila.ac.id\/id\/file\/59199",
                  "filename": "Global Governance (unbara).pdf",
                  "hash_type": "MD5",
                  "mtime": "2018-01-26 14:10:40",
                  "datasetid": "document",
                  "fileid": 59199,
                  "mime_type": "application\/pdf",
                  "hash": "7e51767bb7a2905764e992871aec9986"
                }
            ],
            "format": "text"
          }
      ],
      "official_url": "https:\/\/jodfisipunbara.files.wordpress.com\/2012\/07\/5-robi-oke-hal-1-7.pdf",
      "lastmod": "2018-01-29 04:11:24"
    },
    {
      "date_type": "published",
      "event_title": "seminar hasil hasil penelitian dan pengabdian kepada masyarakat",
      "subjects": [
        "AC"
      ],
      "uri": "http:\/\/repository.lppm.unila.ac.id\/id\/eprint\/17894",
      "date": 2011,
      "abstract": "Hasil Penilaian Sejawat Sebidang Atau Peer Review Karya Ilmiah: Prosiding nasional",
      "event_type": "conference",
      "divisions": [
        "FISIP3"
      ],
      "dir": "disk0\/00\/01\/78\/94",
      "rev_number": 9,
      "ispublished": "pub",
      "full_text_status": "public",
      "status_changed": "2020-02-05 04:12:09",
      "metadata_visibility": "show",
      "datestamp": "2020-02-05 04:12:09",
      "eprint_status": "archive",
      "eprintid": 17894,
      "lastmod": "2020-05-15 07:33:12",
      "documents": [
          {
            "language": "en",
            "mime_type": "application\/pdf",
            "rev_number": 1,
            "format": "text",
            "files": [
                {
                  "datasetid": "document",
                  "fileid": 185929,
                  "mime_type": "application\/pdf",
                  "hash": "e5cc25b1dabcd8d503c4bc6c6a304995",
                  "objectid": 32955,
                  "filesize": 717599,
                  "uri": "http:\/\/repository.lppm.unila.ac.id\/id\/file\/185929",
                  "filename": "13. Ari D Reviewer Independensi.pdf",
                  "hash_type": "MD5",
                  "mtime": "2020-05-15 07:33:12"
                }
            ],
            "main": "13. Ari D Reviewer Independensi.pdf",
            "docid": 32955,
            "security": "public",
            "uri": "http:\/\/repository.lppm.unila.ac.id\/id\/document\/32955",
            "pos": 1,
            "eprintid": 17894,
            "placement": 1
          }
      ],
      "userid": 880,
      "title": "independensi pemberian suara oleh mahasiswi pemilih pemula",
      "refereed": "TRUE",
      "pres_type": "paper",
      "type": "conference_item",
      "creators": [
        {
          "name": {
            "honourific": null,
            "lineage": null,
            "family": "Darmastuti",
            "given": "Ari"
          }
        }
      ]
    },
    {
      "documents": [
          {
            "rev_number": 1,
            "language": "en",
            "mime_type": "application\/pdf",
            "format": "text",
            "files": [
                {
                  "filesize": 2855077,
                  "objectid": 31021,
                  "filename": "13. Similarity Dr. Ari Independensi_Pemberian_Suara_oleh_Mahasiswi_Pemili(1)(1).pdf",
                  "uri": "http:\/\/repository.lppm.unila.ac.id\/id\/file\/150709",
                  "hash_type": "MD5",
                  "mtime": "2020-02-05 03:46:46",
                  "fileid": 150709,
                  "datasetid": "document",
                  "hash": "dc6097362f8ef4c5a677153f9ccd6a53",
                  "mime_type": "application\/pdf"
                }
            ],
            "main": "13. Similarity Dr. Ari Independensi_Pemberian_Suara_oleh_Mahasiswi_Pemili(1)(1).pdf",
            "docid": 31021,
            "security": "public",
            "pos": 1,
            "uri": "http:\/\/repository.lppm.unila.ac.id\/id\/document\/31021",
            "eprintid": 17895,
            "placement": 1
          }
      ],
      "lastmod": "2020-02-05 08:36:56",
      "userid": 880,
      "metadata_visibility": "show",
      "eprint_status": "archive",
      "eprintid": 17895,
      "datestamp": "2020-02-05 08:36:56",
      "event_location": "universitas indonesia",
      "refereed": "TRUE",
      "event_dates": "21 september 2011",
      "title": "independensi pemberian suara oleh mahasiswi pemilih pemula",
      "creators": [
        {
          "name": {
            "family": "Darmastuti",
            "lineage": null,
            "honourific": null,
            "given": "Ari"
          }
        }
      ],
      "pres_type": "paper",
      "type": "conference_item",
      "uri": "http:\/\/repository.lppm.unila.ac.id\/id\/eprint\/17895",
      "date": 2011,
      "abstract": "Similarity",
      "event_title": "seminar hasil hasil penelitian dan pengabdian kepada masyarakat",
      "subjects": [
        "AC"
      ],
      "date_type": "published",
      "rev_number": 7,
      "ispublished": "pub",
      "status_changed": "2020-02-05 08:36:56",
      "full_text_status": "public",
      "event_type": "conference",
      "divisions": [
        "FISIP3"
      ],
      "dir": "disk0\/00\/01\/78\/95"
    },
    {
      "status_changed": "2020-02-05 04:08:36",
      "full_text_status": "public",
      "rev_number": 7,
      "ispublished": "pub",
      "publication": "Jurnal Administratio",
      "divisions": [
        "FISIP3"
      ],
      "dir": "disk0\/00\/01\/78\/92",
      "volume": 2,
      "abstract": "Hasil Penilaian Sejawat Sebidang Atau Peer Review Karya Ilmiah: Jurnal Nasional Tak Akreditasi",
      "date": 2011,
      "uri": "http:\/\/repository.lppm.unila.ac.id\/id\/eprint\/17892",
      "subjects": [
        "AC"
      ],
      "date_type": "published",
      "creators": [
        {
          "name": {
            "honourific": null,
            "family": "Darmastuti",
            "lineage": null,
            "given": "Ari"
          }
        }
      ],
      "type": "article",
      "refereed": "TRUE",
      "title": "parochialisme; women in the decision making of coastal resource management in two coastal areas in lampung province, indonesia",
      "number": 1,
      "userid": 880,
      "documents": [
          {
            "placement": 1,
            "eprintid": 17892,
            "uri": "http:\/\/repository.lppm.unila.ac.id\/id\/document\/32954",
            "pos": 1,
            "security": "public",
            "files": [
                {
                  "uri": "http:\/\/repository.lppm.unila.ac.id\/id\/file\/185927",
                  "filename": "12. Ari D Reviewer Parochalism.pdf",
                  "objectid": 32954,
                  "filesize": 690787,
                  "mtime": "2020-05-15 07:32:23",
                  "hash_type": "MD5",
                  "mime_type": "application\/pdf",
                  "hash": "c075869d50b5c29b6126f0e7a8df7452",
                  "fileid": 185927,
                  "datasetid": "document"
                }
            ],
            "main": "12. Ari D Reviewer Parochalism.pdf",
            "docid": 32954,
            "format": "text",
            "language": "en",
            "mime_type": "application\/pdf",
            "rev_number": 1
          }
      ],
      "lastmod": "2020-05-15 07:32:23",
      "eprintid": 17892,
      "eprint_status": "archive",
      "datestamp": "2020-02-05 04:08:36",
      "metadata_visibility": "show"
    },
    {
      "subjects": [
        "AC"
      ],
      "date_type": "published",
      "abstract": "Similarity",
      "date": 2011,
      "uri": "http:\/\/repository.lppm.unila.ac.id\/id\/eprint\/17893",
      "divisions": [
        "FISIP3"
      ],
      "publication": "Jurnal Administratio",
      "dir": "disk0\/00\/01\/78\/93",
      "status_changed": "2020-02-05 04:09:35",
      "full_text_status": "public",
      "rev_number": 6,
      "ispublished": "pub",
      "eprintid": 17893,
      "eprint_status": "archive",
      "datestamp": "2020-02-05 04:09:35",
      "metadata_visibility": "show",
      "userid": 880,
      "documents": [
          {
            "placement": 1,
            "eprintid": 17893,
            "uri": "http:\/\/repository.lppm.unila.ac.id\/id\/document\/31019",
            "pos": 1,
            "security": "public",
            "docid": 31019,
            "main": "12. Similarity Dr. Ari D Parochialism_Women_in_the_DEcision_Making_of_Coast.pdf",
            "files": [
                {
                  "mime_type": "application\/pdf",
                  "hash": "d4e5cd75032df50476206693801a5685",
                  "fileid": 150695,
                  "datasetid": "document",
                  "mtime": "2020-02-05 03:32:22",
                  "hash_type": "MD5",
                  "uri": "http:\/\/repository.lppm.unila.ac.id\/id\/file\/150695",
                  "filename": "12. Similarity Dr. Ari D Parochialism_Women_in_the_DEcision_Making_of_Coast.pdf",
                  "objectid": 31019,
                  "filesize": 4282456
                }
            ],
            "format": "text",
            "language": "en",
            "mime_type": "application\/pdf",
            "rev_number": 1
          }
      ],
      "lastmod": "2020-02-05 04:09:35",
      "type": "article",
      "creators": [
        {
          "name": {
            "honourific": null,
            "lineage": null,
            "family": "Darmastuti",
            "given": "Ari"
          }
        }
      ],
      "refereed": "TRUE",
      "title": "parochialisme; women in the decision making of coastal resource management in two coastal areas in lampung province, indonesia"
    },
    {
      "creators": [
        {
          "name": {
            "given": "Hertanto",
            "honourific": null,
            "lineage": null,
            "family": "Hertanto"
          },
          "id": "hertanto.1960@fisip.unila.ac.id"
        }
      ],
      "type": "article",
      "title": "PEMILUKADA LAMPUNG PASCA-ORDE BARU:\r\nPERSAINGAN PARPOL, KONFLIK ELIT, DAN PERILAKU PEMILIH",
      "contact_email": "jurnal@mahkamahkonstitusi.go.id.",
      "metadata_visibility": "show",
      "lastmod": "2020-03-03 09:10:24",
      "publication": "Jurnal Konstitusi",
      "divisions": [
        "FISIP3"
      ],
      "dir": "disk0\/00\/01\/83\/11",
      "status_changed": "2020-03-03 09:10:24",
      "rev_number": 7,
      "subjects": [
        "JA"
      ],
      "date_type": "published",
      "volume": "III",
      "uri": "http:\/\/repository.lppm.unila.ac.id\/id\/eprint\/18311",
      "refereed": "TRUE",
      "eprint_status": "archive",
      "eprintid": 18311,
      "id_number": 2123529000,
      "datestamp": "2020-03-03 09:10:24",
      "pagerange": "53-80",
      "number": 1,
      "userid": 813,
      "documents": [
          {
            "placement": 1,
            "eprintid": 18311,
            "uri": "http:\/\/repository.lppm.unila.ac.id\/id\/document\/31462",
            "pos": 1,
            "security": "public",
            "docid": 31462,
            "main": "Pemilukada Lampung Pasca-Orde Baru.pdf",
            "files": [
                {
                  "filesize": 4704287,
                  "objectid": 31462,
                  "uri": "http:\/\/repository.lppm.unila.ac.id\/id\/file\/154092",
                  "filename": "Pemilukada Lampung Pasca-Orde Baru.pdf",
                  "hash_type": "MD5",
                  "mtime": "2020-02-28 14:38:47",
                  "fileid": 154092,
                  "datasetid": "document",
                  "mime_type": "application\/pdf",
                  "hash": "16495e40dd75fdcb53f1e5ec96228d9f"
                }
            ],
            "format": "text",
            "language": "en",
            "mime_type": "application\/pdf",
            "rev_number": 1
          }
      ],
      "official_url": "http:\/\/www.mahkamahkonstitusi.go.id",
      "publisher": "Kepaniteraan dan Sekretariat Jenderal Mahkamah Konstitusi Republik Indonesia",
      "related_url": [
        {
          "type": "pub",
          "url": "http:\/\/www.mahkamahkonstitusi.go.id"
        }
      ],
      "full_text_status": "public",
      "issn": "1829-7706",
      "ispublished": "pub",
      "abstract": "ABSTRACT\r\n\r\n\r\nThis article describes the political dynamics of the Lampung Province in the post of the new order era. Its described about the political role of local elites, and the conflict that took place in the local election. It appears that more conflicts triggered by the seizure of power rather than policy debate to fight for the interests of the people. Political parties tend to be a vehicle of political elites, rather than a means to fight for the development purposes. Meanwhile, among voters likely still to be affected by primordial considerations in choosing their leaders. Therefore, the process of democracy in Lampung Province move on procedural level and not substantial. However, local elections in the area (2005, 2007, 2008, 2010) has put the rotation of political power without violence.\r\n\r\nKey Words: Political Conflict, Local Election, Democracy.",
      "date": "2011-06"
    },
    {
      "refereed": "FALSE",
      "title": "Indonesia needs powerful KPK",
      "creators": [
        {
          "name": {
            "lineage": null,
            "family": "Kurniawan",
            "honourific": null,
            "given": "Budi"
          },
          "id": "budi.kurniawan@fisip.unila.ac.id"
        }
      ],
      "type": "article",
      "metadata_visibility": "show",
      "eprint_status": "archive",
      "eprintid": 21189,
      "datestamp": "2020-05-30 19:58:14",
      "documents": [
          {
            "content": "published",
            "language": "en",
            "mime_type": "text\/html",
            "rev_number": 3,
            "format": "text",
            "main": "indonesia-needs-powerful-kpk.html",
            "docid": 34572,
            "files": [
                {
                  "fileid": 197332,
                  "datasetid": "document",
                  "mime_type": "text\/html",
                  "hash": "4b6367b0c26fe119cbbca295d09da51c",
                  "filesize": 74148,
                  "objectid": 34572,
                  "uri": "http:\/\/repository.lppm.unila.ac.id\/id\/file\/197332",
                  "filename": "indonesia-needs-powerful-kpk.html",
                  "hash_type": "MD5",
                  "mtime": "2020-05-30 13:27:59"
                }
            ],
            "security": "public",
            "pos": 1,
            "uri": "http:\/\/repository.lppm.unila.ac.id\/id\/document\/34572",
            "eprintid": 21189,
            "placement": 1
          }
      ],
      "lastmod": "2020-05-30 19:58:14",
      "userid": 284,
      "publication": "The Jakarta Post",
      "divisions": [
        "FISIP3"
      ],
      "dir": "disk0\/00\/02\/11\/89",
      "related_url": [
        {
          "url": "https:\/\/www.thejakartapost.com\/news\/2011\/12\/07\/indonesia-needs-powerful-kpk.html"
        }
      ],
      "rev_number": 10,
      "ispublished": "pub",
      "status_changed": "2020-05-30 19:58:14",
      "full_text_status": "public",
      "subjects": [
        "JC",
        "JF",
        "JQ"
      ],
      "date_type": "published",
      "uri": "http:\/\/repository.lppm.unila.ac.id\/id\/eprint\/21189",
      "date": "2011-12-07",
      "abstract": "In his article that appeared in the Nov. 28, 2011 edition of The Jakarta Post, House of Representatives member Fahri Hamzah argues that the Corruption Eradication Commission (KPK) is a very powerful institution in a democratic regime.\r\n\r\nHe further emphasizes that there should be no strong institution or superbody in democratic countries.\r\n\r\nHowever, there is a fallacy in Hamzah’s point of view. The main point is the way Hamzah thinks about democratic regimes. Could democratic countries form strong institutions like the KPK?"
    }
]

